LICENSE
README.md
setup.py
RNAdynamics/__init__.py
RNAdynamics/kinetics.py
RNAdynamics/layers.py
RNAdynamics.egg-info/PKG-INFO
RNAdynamics.egg-info/SOURCES.txt
RNAdynamics.egg-info/dependency_links.txt
RNAdynamics.egg-info/requires.txt
RNAdynamics.egg-info/top_level.txt