Metadata-Version: 2.1
Name: RNAdynamics
Version: 0.1
Summary: Biological prior guided single-cell kinetics inference.
Home-page: https://github.com/poseidonchan/scKinetics
Author: Yanshuo Chen
Author-email: poseidonchan@icloud.com
License: GPL-3.0 License
Platform: any
Requires-Python: >=3.7.1,<3.8
License-File: LICENSE
